orangery/__init__.py
orangery/cli/__init__.py
orangery/cli/adjust.py
orangery/cli/cutfill.py
orangery/cli/geodetic.py
orangery/core/__init__.py
orangery/core/api.py
orangery/core/evaluation.py
orangery/core/filter.py
orangery/core/survey.py
orangery/ops/__init__.py
orangery/ops/correction.py
orangery/ops/geodetic.py
orangery/ops/geometry.py
orangery/ops/text.py
orangery/tools/__init__.py
orangery/tools/console.py
orangery/tools/plotting.py
orangery/tools/units.py
orangery-0.4.1.dist-info/DESCRIPTION.rst
orangery-0.4.1.dist-info/METADATA
orangery-0.4.1.dist-info/RECORD
orangery-0.4.1.dist-info/WHEEL
orangery-0.4.1.dist-info/entry_points.txt
orangery-0.4.1.dist-info/metadata.json
orangery-0.4.1.dist-info/top_level.txt
