Metadata-Version: 2.0
Name: orangery
Version: 0.4.1
Summary: Python library to support analysis of topographic cross-sections
Home-page: http://github.com/mrahnis/orangery
Author: Michael Rahnis
Author-email: michael.rahnis@fandm.edu
License: BSD
Keywords: cross-section,topography,survey,plotting
Platform: UNKNOWN
Classifier: Development Status :: 3 - Alpha
Classifier: License :: OSI Approved :: BSD License
Classifier: Programming Language :: Python
Classifier: Programming Language :: Python :: 2.7
Classifier: Programming Language :: Python :: 3
Classifier: Topic :: Scientific/Engineering :: GIS
Requires-Dist: click
Requires-Dist: matplotlib
Requires-Dist: numpy
Requires-Dist: opusxml
Requires-Dist: pandas
Requires-Dist: shapely
